sksurgerycore/__init__.py
sksurgerycore/__main__.py
sksurgerycore/_version.py
sksurgerycore/algorithms/__init__.py
sksurgerycore/algorithms/errors.py
sksurgerycore/algorithms/pivot.py
sksurgerycore/algorithms/procrustes.py
sksurgerycore/algorithms/vector_math.py
sksurgerycore/configuration/__init__.py
sksurgerycore/configuration/configuration_manager.py
sksurgerycore/io/__init__.py
sksurgerycore/io/load_mps.py
sksurgerycore/transforms/__init__.py
sksurgerycore/transforms/matrix.py
sksurgerycore/transforms/transform_manager.py
sksurgerycore/ui/__init__.py
sksurgerycore/ui/sksurgerycore_command_line.py
sksurgerycore/ui/sksurgerycore_demo.py
sksurgerycore/utilities/__init__.py
sksurgerycore/utilities/file_utilities.py
sksurgerycore/utilities/validate.py
sksurgerycore/utilities/validate_file.py
sksurgerycore/utilities/validate_matrix.py
scikit_surgerycore-0.5.0.dist-info/LICENSE
scikit_surgerycore-0.5.0.dist-info/METADATA
scikit_surgerycore-0.5.0.dist-info/WHEEL
scikit_surgerycore-0.5.0.dist-info/entry_points.txt
scikit_surgerycore-0.5.0.dist-info/top_level.txt
scikit_surgerycore-0.5.0.dist-info/RECORD
